team13hackertype/__init__.py
team13hackertype/__main__.py
team13hackertype/hackertype.py
team13hackertype/penetrate.py
team13hackertype/code_snippets/java.txt
team13hackertype/code_snippets/python.txt
team13hackertype-1.0.4.dist-info/LICENSE
team13hackertype-1.0.4.dist-info/METADATA
team13hackertype-1.0.4.dist-info/WHEEL
team13hackertype-1.0.4.dist-info/top_level.txt
team13hackertype-1.0.4.dist-info/RECORD
