Metadata-Version: 2.1
Name: team13hackertype
Version: 1.0.4
Summary: An example of a package developed with pyenv, built with build using setuptools, uploaded to PyPI using twine, and distributed via pip.
Author: Kedan Zha, Evan Huang, Bruce Wu, Amaan Khwaja
License: GNU GENERAL PUBLIC LICENSE
Project-URL: Homepage, https://github.com/software-students-fall2022/python-package-exercise-project-3-team-13
Project-URL: Repository, https://github.com/software-students-fall2022/python-package-exercise-project-3-team-13.git
Project-URL: Bug Tracker, https://github.com/software-students-fall2022/python-package-exercise-project-3-team-13/issues
Keywords: python,package,build,hackertype
Classifier: Programming Language :: Python :: 3
Classifier: Intended Audience :: Education
Classifier: License :: OSI Approved :: GNU General Public License v3 (GPLv3)
Classifier: Operating System :: OS Independent
Requires-Python: >=3.7
License-File: LICENSE
Requires-Dist: astroid (==2.12.12)
Requires-Dist: attrs (==22.1.0)
Requires-Dist: bleach (==5.0.1)
Requires-Dist: build (==0.9.0)
Requires-Dist: certifi (==2022.9.24)
Requires-Dist: charset-normalizer (==2.1.1)
Requires-Dist: colorama (==0.4.6)
Requires-Dist: commonmark (==0.9.1)
Requires-Dist: dill (==0.3.6)
Requires-Dist: distlib (==0.3.6)
Requires-Dist: docutils (==0.19)
Requires-Dist: exceptiongroup (==1.0.0)
Requires-Dist: filelock (==3.8.0)
Requires-Dist: flake8 (==5.0.4)
Requires-Dist: idna (==3.4)
Requires-Dist: importlib-metadata (==5.0.0)
Requires-Dist: iniconfig (==1.1.1)
Requires-Dist: isort (==5.10.1)
Requires-Dist: jaraco.classes (==3.2.3)
Requires-Dist: keyboard (==0.13.5)
Requires-Dist: keyring (==23.11.0)
Requires-Dist: lazy-object-proxy (==1.8.0)
Requires-Dist: mccabe (==0.7.0)
Requires-Dist: more-itertools (==9.0.0)
Requires-Dist: packaging (==21.3)
Requires-Dist: pep517 (==0.13.0)
Requires-Dist: pkginfo (==1.8.3)
Requires-Dist: platformdirs (==2.5.2)
Requires-Dist: pluggy (==1.0.0)
Requires-Dist: pycodestyle (==2.9.1)
Requires-Dist: pyfiglet (==0.8.post1)
Requires-Dist: pyflakes (==2.5.0)
Requires-Dist: Pygments (==2.13.0)
Requires-Dist: pylint (==2.15.5)
Requires-Dist: pyparsing (==3.0.9)
Requires-Dist: pytest (==7.2.0)
Requires-Dist: pywin32-ctypes (==0.2.0)
Requires-Dist: readme-renderer (==37.3)
Requires-Dist: requests (==2.28.1)
Requires-Dist: requests-toolbelt (==0.10.1)
Requires-Dist: rfc3986 (==2.0.0)
Requires-Dist: rich (==12.6.0)
Requires-Dist: six (==1.16.0)
Requires-Dist: tomli (==2.0.1)
Requires-Dist: tomlkit (==0.11.6)
Requires-Dist: twine (==4.0.1)
Requires-Dist: typing-extensions (==4.4.0)
Requires-Dist: urllib3 (==1.26.12)
Requires-Dist: virtualenv (==20.16.6)
Requires-Dist: webencodings (==0.5.1)
Requires-Dist: wrapt (==1.14.1)
Requires-Dist: zipp (==3.10.0)
Provides-Extra: dev
Requires-Dist: pytest ; extra == 'dev'
